{
	"info": {
		"_postman_id": "661e1d8a-c56e-4eb4-a808-5d7c398b1f4b",
		"name": "runnerman Collection",
		"schema": "https://schema.getpostman.com/json/collection/v2.1.0/collection.json"
	},
	"item": [
		{
			"name": "Test Post",
			"request": {
				"method": "POST",
				"header": [
					{
						"key": "Content-Type",
						"value": "application/json",
						"type": "text"
					}
				],
				"body": {
					"mode": "raw",
					"raw": "{\n    \"a\": \"b\"\n}",
					"options": {
						"raw": {
							"language": "json"
						}
					}
				},
				"url": {
					"raw": "https://postman-echo.com/post",
					"protocol": "https",
					"host": [
						"postman-echo",
						"com"
					],
					"path": [
						"post"
					]
				}
			},
			"response": []
		},
		{
			"name": "Test Put",
			"request": {
				"method": "PUT",
				"header": [],
				"body": {
					"mode": "raw",
					"raw": "{{json}}",
					"options": {
						"raw": {
							"language": "json"
						}
					}
				},
				"url": {
					"raw": "https://postman-echo.com/put",
					"protocol": "https",
					"host": [
						"postman-echo",
						"com"
					],
					"path": [
						"put"
					]
				}
			},
			"response": []
		}
	],
	"event": [
		{
			"listen": "prerequest",
			"script": {
				"id": "a27bde81-8825-4b4b-8dc7-6af697ff03c7",
				"type": "text/javascript",
				"exec": [
					""
				]
			}
		},
		{
			"listen": "test",
			"script": {
				"id": "d316c649-e974-49a6-a91f-bde204c986fa",
				"type": "text/javascript",
				"exec": [
					""
				]
			}
		}
	],
	"protocolProfileBehavior": {}
}